piri3/__init__.py
piri3/casting.py
piri3/collection_handlers.py
piri3/common.py
piri3/constants.py
piri3/functions.py
piri3/handlers.py
piri3/iso.py
piri3/mapper.py
piri3/process.py
piri3/schema.json
piri3/schema.py
piri3/valuetypes.py
piri3-3.0.4.dist-info/LICENSE
piri3-3.0.4.dist-info/METADATA
piri3-3.0.4.dist-info/WHEEL
piri3-3.0.4.dist-info/RECORD
