Metadata-Version: 2.1
Name: piri3
Version: 3.0.4
Summary: Configurable and documentable Json transformation and mapping
Home-page: https://github.com/greenbird/piri
License: MIT
Keywords: Json mapping,data transformation,json to json,dict to dict,configurable
Author: Shaun Patterson
Author-email: thomas.borgen@greenbird.com
Requires-Python: >=3.9,<4.0
Classifier: Development Status :: 5 - Production/Stable
Classifier: Intended Audience :: Developers
Classifier: License :: OSI Approved :: MIT License
Classifier: Operating System :: OS Independent
Classifier: Programming Language :: Python :: 3
Classifier: Programming Language :: Python :: 3.9
Classifier: Programming Language :: Python :: 3.10
Classifier: Programming Language :: Python :: 3.11
Classifier: Topic :: Software Development :: Libraries :: Python Modules
Classifier: Topic :: Utilities
Requires-Dist: jsonschema (>=3.2.0,<4.0.0)
Requires-Dist: pycountry (==19.8.18)
Requires-Dist: returns (>=0.22.0,<0.23.0)
Requires-Dist: typing_extensions (>=4.0)
Project-URL: Documentation, https://greenbird.github.io/piri/
Project-URL: Repository, https://github.com/greenbird/piri
